cobisolv/__init__.py
cobisolv/formulate.py
cobisolv/optimizationProblem.py
cobisolv/cobi_cloud/__init__.py
cobisolv/cobi_cloud/cobi_cloud.py
cobisolv-1.0.dist-info/METADATA
cobisolv-1.0.dist-info/WHEEL
cobisolv-1.0.dist-info/top_level.txt
cobisolv-1.0.dist-info/RECORD
