Metadata-Version: 2.1
Name: cobisolv
Version: 1.0
Summary: Create and solve optimization problems. Property of COBI Inc.
Home-page: https://github.com/cobi-inc/CobiCloud/tree/main
Author: William Cho
Author-email: william.cho@cobi.tech
License: UNKNOWN
Platform: UNKNOWN
Classifier: Programming Language :: Python :: 3
Classifier: License :: OSI Approved :: MIT License
Classifier: Operating System :: OS Independent
Requires-Python: >=3.6
